{"node":{"00ac6dcfd4c6a493fd0a71d97d8791595222deb337":{"workers":{"app/companies/page":{"moduleId":"9230","async":false}},"layer":{"app/companies/page":"rsc"},"filename":"app/companies/page.tsx","exportedName":"$$RSC_SERVER_ACTION_0"},"0047ba2cf86eecfee1c5404831cfa46b7faae47ab7":{"workers":{"app/companies/page":{"moduleId":"9230","async":false}},"layer":{"app/companies/page":"rsc"},"filename":"actions/seed.ts","exportedName":"seedData"},"005142cf0096f2d86c8c4fb337a89222dfb068d610":{"workers":{"app/(auth)/signup/page":{"moduleId":"5943","async":false},"app/(auth)/login/page":{"moduleId":"5943","async":false}},"layer":{"app/(auth)/signup/page":"action-browser","app/(auth)/login/page":"action-browser"},"filename":"actions/auth.ts","exportedName":"logout"},"602d22600e3dbb3df8fcb3c51cdeb797b9582b8aed":{"workers":{"app/(auth)/signup/page":{"moduleId":"5943","async":false},"app/(auth)/login/page":{"moduleId":"5943","async":false}},"layer":{"app/(auth)/signup/page":"action-browser","app/(auth)/login/page":"action-browser"},"filename":"actions/auth.ts","exportedName":"login"},"60986f7cc5852f05018fcffa886fd553053d56c768":{"workers":{"app/(auth)/signup/page":{"moduleId":"5943","async":false},"app/(auth)/login/page":{"moduleId":"5943","async":false}},"layer":{"app/(auth)/signup/page":"action-browser","app/(auth)/login/page":"action-browser"},"filename":"actions/auth.ts","exportedName":"signup"}},"edge":{},"encryptionKey":"u409VvBYar77109Sj2CogSQdPCACcQdMGBkL1lmmK+Q="}